polyaxon_helper/__init__.py
tests/__init__.py
tests/test_helpers.py
polyaxon_helper-0.5.0.dist-info/LICENSE
polyaxon_helper-0.5.0.dist-info/METADATA
polyaxon_helper-0.5.0.dist-info/WHEEL
polyaxon_helper-0.5.0.dist-info/top_level.txt
polyaxon_helper-0.5.0.dist-info/RECORD
